procedural/__init__.py
procedural/client.py
procedural/file_handling.py
procedural/utils/__init__.py
procedural/utils/secrets.py
procedural-0.1.1.dist-info/WHEEL
procedural-0.1.1.dist-info/METADATA
procedural-0.1.1.dist-info/RECORD
